npdep_icmp_client/__init__.py
npdep_icmp_client/__main__.py
npdep_icmp_client/args/Args.py
npdep_icmp_client/args/__init__.py
npdep_icmp_client/client/Client.py
npdep_icmp_client/client/__init__.py
npdep_icmp_client/output/Output.py
npdep_icmp_client/output/__init__.py
npdep_icmp_client/type/IcmpType.py
npdep_icmp_client/type/RequestType.py
npdep_icmp_client/type/__init__.py
npdep_icmp_client/util/Util.py
npdep_icmp_client/util/__init__.py
npdep_icmp_client-1.0.0.dist-info/METADATA
npdep_icmp_client-1.0.0.dist-info/WHEEL
npdep_icmp_client-1.0.0.dist-info/entry_points.txt
npdep_icmp_client-1.0.0.dist-info/top_level.txt
npdep_icmp_client-1.0.0.dist-info/RECORD
