Metadata-Version: 2.1
Name: npdep_icmp_client
Version: 1.0.0
Summary: A client to exfiltrate files through ICMP messages
Classifier: Operating System :: OS Independent 
Classifier: Programming Language :: Python :: 3 
